indexwarrior/__init__.py
indexwarrior/_version.py
indexwarrior/errors.py
indexwarrior/main.py
indexwarrior/utils.py
indexwarrior-0.2.1.data/scripts/indexwarrior
indexwarrior-0.2.1.dist-info/DESCRIPTION.rst
indexwarrior-0.2.1.dist-info/METADATA
indexwarrior-0.2.1.dist-info/RECORD
indexwarrior-0.2.1.dist-info/WHEEL
indexwarrior-0.2.1.dist-info/metadata.json
indexwarrior-0.2.1.dist-info/top_level.txt
