Metadata-Version: 2.0
Name: indexwarrior
Version: 0.2.1
Summary: Tool to operate GrimoireLab ES indexes
Home-page: https://gitlab.com/devops/indexwarrior
Author: Bitergia
Author-email: lcanas@bitergia.com
License: GPLv3
Keywords: development repositories analytics
Platform: UNKNOWN
Classifier: Development Status :: 5 - Production/Stable
Classifier: Intended Audience :: Developers
Classifier: Topic :: Software Development
Classifier: License :: OSI Approved :: GNU General Public License v3 or later (GPLv3+)
Classifier: Programming Language :: Python :: 3.4
Requires-Dist: certifi (==2016.9.26)
Requires-Dist: colorama (==0.3.9)
Requires-Dist: elasticsearch (==5.1.0)
Requires-Dist: elasticsearch-dsl (==5.1.0)
Requires-Dist: prettytable (==0.7.2)
Requires-Dist: httpretty (==0.8.14)
